{
  "type": "FeatureCollection",
  "features": [
    {
      "type": "Feature",
      "geometry": {
        "type": "Point",
        "coordinates": [
          19.958,
          60.2515
        ]
      },
      "properties": {
        "region_schema": "fi_health_district",
        "region_parent": "fi",
        "region_child": "ahvenanmaa",
        "area": 0.2105999999999987,
        "bounding_box": [
          19.658,
          60.076,
          20.258,
          60.427
        ],
        "point": [
          19.958,
          60.2515
        ],
        "labels": {
          "en": "Ahvenanmaa"
        },
        "population": 27322
      }
    },
    {
      "type": "Feature",
      "geometry": {
        "type": "Point",
        "coordinates": [
          20.122,
          60.048
        ]
      },
      "properties": {
        "region_schema": "fi_health_district",
        "region_parent": "fi",
        "region_child": "ahvenanmaa",
        "area": 0.022439999999999953,
        "bounding_box": [
          20.02,
          59.993,
          20.224,
          60.103
        ],
        "point": [
          20.122,
          60.048
        ],
        "labels": {
          "en": "Ahvenanmaa"
        },
        "population": 27322
      }
    },
    {
      "type": "Feature",
      "geometry": {
        "type": "Point",
        "coordinates": [
          19.5975,
          60.2095
        ]
      },
      "properties": {
        "region_schema": "fi_health_district",
        "region_parent": "fi",
        "region_child": "ahvenanmaa",
        "area": 0.0208750000000002,
        "bounding_box": [
          19.514,
          60.147,
          19.681,
          60.272
        ],
        "point": [
          19.5975,
          60.2095
        ],
        "labels": {
          "en": "Ahvenanmaa"
        },
        "population": 27322
      }
    },
    {
      "type": "Feature",
      "geometry": {
        "type": "Point",
        "coordinates": [
          20.3815,
          60.24
        ]
      },
      "properties": {
        "region_schema": "fi_health_district",
        "region_parent": "fi",
        "region_child": "ahvenanmaa",
        "area": 0.008685999999999772,
        "bounding_box": [
          20.331,
          60.197,
          20.432,
          60.283
        ],
        "point": [
          20.3815,
          60.24
        ],
        "labels": {
          "en": "Ahvenanmaa"
        },
        "population": 27322
      }
    },
    {
      "type": "Feature",
      "geometry": {
        "type": "Point",
        "coordinates": [
          20.247500000000002,
          60.114
        ]
      },
      "properties": {
        "region_schema": "fi_health_district",
        "region_parent": "fi",
        "region_child": "ahvenanmaa",
        "area": 0.008170000000000068,
        "bounding_box": [
          20.2,
          60.071,
          20.295,
          60.157
        ],
        "point": [
          20.247500000000002,
          60.114
        ],
        "labels": {
          "en": "Ahvenanmaa"
        },
        "population": 27322
      }
    },
    {
      "type": "Feature",
      "geometry": {
        "type": "Point",
        "coordinates": [
          20.551000000000002,
          60.034
        ]
      },
      "properties": {
        "region_schema": "fi_health_district",
        "region_parent": "fi",
        "region_child": "ahvenanmaa",
        "area": 0.006159999999999879,
        "bounding_box": [
          20.496,
          60.006,
          20.606,
          60.062
        ],
        "point": [
          20.551000000000002,
          60.034
        ],
        "labels": {
          "en": "Ahvenanmaa"
        },
        "population": 27322
      }
    },
    {
      "type": "Feature",
      "geometry": {
        "type": "Point",
        "coordinates": [
          20.786,
          60.257999999999996
        ]
      },
      "properties": {
        "region_schema": "fi_health_district",
        "region_parent": "fi",
        "region_child": "ahvenanmaa",
        "area": 0.005631999999999839,
        "bounding_box": [
          20.742,
          60.226,
          20.83,
          60.29
        ],
        "point": [
          20.786,
          60.257999999999996
        ],
        "labels": {
          "en": "Ahvenanmaa"
        },
        "population": 27322
      }
    },
    {
      "type": "Feature",
      "geometry": {
        "type": "Point",
        "coordinates": [
          20.338,
          59.998000000000005
        ]
      },
      "properties": {
        "region_schema": "fi_health_district",
        "region_parent": "fi",
        "region_child": "ahvenanmaa",
        "area": 0.0036799999999998717,
        "bounding_box": [
          20.292,
          59.978,
          20.384,
          60.018
        ],
        "point": [
          20.338,
          59.998000000000005
        ],
        "labels": {
          "en": "Ahvenanmaa"
        },
        "population": 27322
      }
    },
    {
      "type": "Feature",
      "geometry": {
        "type": "Point",
        "coordinates": [
          20.499000000000002,
          60.0475
        ]
      },
      "properties": {
        "region_schema": "fi_health_district",
        "region_parent": "fi",
        "region_child": "ahvenanmaa",
        "area": 0.002442000000000146,
        "bounding_box": [
          20.462,
          60.031,
          20.536,
          60.064
        ],
        "point": [
          20.499000000000002,
          60.0475
        ],
        "labels": {
          "en": "Ahvenanmaa"
        },
        "population": 27322
      }
    },
    {
      "type": "Feature",
      "geometry": {
        "type": "Point",
        "coordinates": [
          28.6485,
          61.26649999999999
        ]
      },
      "properties": {
        "region_schema": "fi_health_district",
        "region_parent": "fi",
        "region_child": "etelä-karjala",
        "area": 3.5742450000000003,
        "bounding_box": [
          27.153,
          60.669,
          30.144,
          61.864
        ],
        "point": [
          28.6485,
          61.26649999999999
        ],
        "labels": {
          "en": "Etelä-Karjala"
        },
        "population": 130773
      }
    },
    {
      "type": "Feature",
      "geometry": {
        "type": "Point",
        "coordinates": [
          23.0635,
          62.739
        ]
      },
      "properties": {
        "region_schema": "fi_health_district",
        "region_parent": "fi",
        "region_child": "etelä-pohjanmaa",
        "area": 4.610166,
        "bounding_box": [
          21.545,
          61.98,
          24.582,
          63.498
        ],
        "point": [
          23.0635,
          62.739
        ],
        "labels": {
          "en": "Etelä-Pohjanmaa"
        },
        "population": 201782
      }
    },
    {
      "type": "Feature",
      "geometry": {
        "type": "Point",
        "coordinates": [
          27.5165,
          61.841
        ]
      },
      "properties": {
        "region_schema": "fi_health_district",
        "region_parent": "fi",
        "region_child": "etelä-savo",
        "area": 3.5703980000000017,
        "bounding_box": [
          26.221,
          61.152,
          28.812,
          62.53
        ],
        "point": [
          27.5165,
          61.841
        ],
        "labels": {
          "en": "Etelä-Savo"
        },
        "population": 100389
      }
    },
    {
      "type": "Feature",
      "geometry": {
        "type": "Point",
        "coordinates": [
          24.6965,
          60.322500000000005
        ]
      },
      "properties": {
        "region_schema": "fi_health_district",
        "region_parent": "fi",
        "region_child": "hus",
        "area": 3.676524999999991,
        "bounding_box": [
          22.849,
          59.825,
          26.544,
          60.82
        ],
        "point": [
          24.6965,
          60.322500000000005
        ],
        "labels": {
          "en": "HUS"
        },
        "population": 1611742
      }
    },
    {
      "type": "Feature",
      "geometry": {
        "type": "Point",
        "coordinates": [
          25.981,
          60.313
        ]
      },
      "properties": {
        "region_schema": "fi_health_district",
        "region_parent": "fi",
        "region_child": "hus",
        "area": 0.007380000000000055,
        "bounding_box": [
          25.936,
          60.272,
          26.026,
          60.354
        ],
        "point": [
          25.981,
          60.313
        ],
        "labels": {
          "en": "HUS"
        },
        "population": 1611742
      }
    },
    {
      "type": "Feature",
      "geometry": {
        "type": "Point",
        "coordinates": [
          25.614,
          60.266
        ]
      },
      "properties": {
        "region_schema": "fi_health_district",
        "region_parent": "fi",
        "region_child": "hus",
        "area": 0.0065119999999999015,
        "bounding_box": [
          25.57,
          60.229,
          25.658,
          60.303
        ],
        "point": [
          25.614,
          60.266
        ],
        "labels": {
          "en": "HUS"
        },
        "population": 1611742
      }
    },
    {
      "type": "Feature",
      "geometry": {
        "type": "Point",
        "coordinates": [
          28.779,
          61.9725
        ]
      },
      "properties": {
        "region_schema": "fi_health_district",
        "region_parent": "fi",
        "region_child": "itä-savo",
        "area": 1.6358759999999954,
        "bounding_box": [
          27.861,
          61.527,
          29.697,
          62.418
        ],
        "point": [
          28.779,
          61.9725
        ],
        "labels": {
          "en": "Itä-Savo"
        },
        "population": 42044
      }
    },
    {
      "type": "Feature",
      "geometry": {
        "type": "Point",
        "coordinates": [
          28.66,
          64.595
        ]
      },
      "properties": {
        "region_schema": "fi_health_district",
        "region_parent": "fi",
        "region_child": "kainuu",
        "area": 7.011672000000017,
        "bounding_box": [
          26.767,
          63.669,
          30.553,
          65.521
        ],
        "point": [
          28.66,
          64.595
        ],
        "labels": {
          "en": "Kainuu"
        },
        "population": 73171
      }
    },
    {
      "type": "Feature",
      "geometry": {
        "type": "Point",
        "coordinates": [
          24.198500000000003,
          60.938500000000005
        ]
      },
      "properties": {
        "region_schema": "fi_health_district",
        "region_parent": "fi",
        "region_child": "kanta-häme",
        "area": 1.6410790000000077,
        "bounding_box": [
          23.137,
          60.552,
          25.26,
          61.325
        ],
        "point": [
          24.198500000000003,
          60.938500000000005
        ],
        "labels": {
          "en": "Kanta-Häme"
        },
        "population": 179285
      }
    },
    {
      "type": "Feature",
      "geometry": {
        "type": "Point",
        "coordinates": [
          24.0415,
          63.604
        ]
      },
      "properties": {
        "region_schema": "fi_health_district",
        "region_parent": "fi",
        "region_child": "keski-pohjanmaa",
        "area": 2.3726559999999988,
        "bounding_box": [
          22.826,
          63.116,
          25.257,
          64.092
        ],
        "point": [
          24.0415,
          63.604
        ],
        "labels": {
          "en": "Keski-Pohjanmaa"
        },
        "population": 78720
      }
    },
    {
      "type": "Feature",
      "geometry": {
        "type": "Point",
        "coordinates": [
          25.3945,
          62.608999999999995
        ]
      },
      "properties": {
        "region_schema": "fi_health_district",
        "region_parent": "fi",
        "region_child": "keski-suomi",
        "area": 5.531526000000003,
        "bounding_box": [
          24.013,
          61.608,
          26.776,
          63.61
        ],
        "point": [
          25.3945,
          62.608999999999995
        ],
        "labels": {
          "en": "Keski-Suomi"
        },
        "population": 259526
      }
    },
    {
      "type": "Feature",
      "geometry": {
        "type": "Point",
        "coordinates": [
          27.1125,
          60.8625
        ]
      },
      "properties": {
        "region_schema": "fi_health_district",
        "region_parent": "fi",
        "region_child": "kymenlaakso",
        "area": 1.5127769999999932,
        "bounding_box": [
          26.234,
          60.432,
          27.991,
          61.293
        ],
        "point": [
          27.1125,
          60.8625
        ],
        "labels": {
          "en": "Kymenlaakso"
        },
        "population": 160464
      }
    },
    {
      "type": "Feature",
      "geometry": {
        "type": "Point",
        "coordinates": [
          25.2845,
          67.89699999999999
        ]
      },
      "properties": {
        "region_schema": "fi_health_district",
        "region_parent": "fi",
        "region_child": "lappi",
        "area": 41.570280000000096,
        "bounding_box": [
          20.552,
          65.701,
          30.017,
          70.093
        ],
        "point": [
          25.2845,
          67.89699999999999
        ],
        "labels": {
          "en": "Lappi"
        },
        "population": 118216
      }
    },
    {
      "type": "Feature",
      "geometry": {
        "type": "Point",
        "coordinates": [
          24.855,
          66.1765
        ]
      },
      "properties": {
        "region_schema": "fi_health_district",
        "region_parent": "fi",
        "region_child": "länsi-pohja",
        "area": 2.857896000000004,
        "bounding_box": [
          23.643,
          65.587,
          26.067,
          66.766
        ],
        "point": [
          24.855,
          66.1765
        ],
        "labels": {
          "en": "Länsi-Pohja"
        },
        "population": 60498
      }
    },
    {
      "type": "Feature",
      "geometry": {
        "type": "Point",
        "coordinates": [
          24.015,
          61.721000000000004
        ]
      },
      "properties": {
        "region_schema": "fi_health_district",
        "region_parent": "fi",
        "region_child": "pirkanmaa",
        "area": 4.692408000000004,
        "bounding_box": [
          22.434,
          60.979,
          25.596,
          62.463
        ],
        "point": [
          24.015,
          61.721000000000004
        ],
        "labels": {
          "en": "Pirkanmaa"
        },
        "population": 549897
      }
    },
    {
      "type": "Feature",
      "geometry": {
        "type": "Point",
        "coordinates": [
          29.916,
          62.802
        ]
      },
      "properties": {
        "region_schema": "fi_health_district",
        "region_parent": "fi",
        "region_child": "pohjois-karjala",
        "area": 7.218719999999986,
        "bounding_box": [
          28.245,
          61.722,
          31.587,
          63.882
        ],
        "point": [
          29.916,
          62.802
        ],
        "labels": {
          "en": "Pohjois-Karjala"
        },
        "population": 168321
      }
    },
    {
      "type": "Feature",
      "geometry": {
        "type": "Point",
        "coordinates": [
          26.866500000000002,
          64.95750000000001
        ]
      },
      "properties": {
        "region_schema": "fi_health_district",
        "region_parent": "fi",
        "region_child": "pohjois-pohjanmaa",
        "area": 20.001951000000023,
        "bounding_box": [
          23.595,
          63.429,
          30.138,
          66.486
        ],
        "point": [
          26.866500000000002,
          64.95750000000001
        ],
        "labels": {
          "en": "Pohjois-Pohjanmaa"
        },
        "population": 421392
      }
    },
    {
      "type": "Feature",
      "geometry": {
        "type": "Point",
        "coordinates": [
          24.799500000000002,
          65.01849999999999
        ]
      },
      "properties": {
        "region_schema": "fi_health_district",
        "region_parent": "fi",
        "region_child": "pohjois-pohjanmaa",
        "area": 0.07451100000000256,
        "bounding_box": [
          24.556,
          64.942,
          25.043,
          65.095
        ],
        "point": [
          24.799500000000002,
          65.01849999999999
        ],
        "labels": {
          "en": "Pohjois-Pohjanmaa"
        },
        "population": 421392
      }
    },
    {
      "type": "Feature",
      "geometry": {
        "type": "Point",
        "coordinates": [
          27.569,
          63.096500000000006
        ]
      },
      "properties": {
        "region_schema": "fi_health_district",
        "region_parent": "fi",
        "region_child": "pohjois-savo",
        "area": 5.752098000000022,
        "bounding_box": [
          26.04,
          62.156,
          29.098,
          64.037
        ],
        "point": [
          27.569,
          63.096500000000006
        ],
        "labels": {
          "en": "Pohjois-Savo"
        },
        "population": 249815
      }
    },
    {
      "type": "Feature",
      "geometry": {
        "type": "Point",
        "coordinates": [
          25.6995,
          61.1625
        ]
      },
      "properties": {
        "region_schema": "fi_health_district",
        "region_parent": "fi",
        "region_child": "päijät-häme",
        "area": 2.033269,
        "bounding_box": [
          24.86,
          60.557,
          26.539,
          61.768
        ],
        "point": [
          25.6995,
          61.1625
        ],
        "labels": {
          "en": "Päijät-Häme"
        },
        "population": 216439
      }
    },
    {
      "type": "Feature",
      "geometry": {
        "type": "Point",
        "coordinates": [
          22.1505,
          61.606
        ]
      },
      "properties": {
        "region_schema": "fi_health_district",
        "region_parent": "fi",
        "region_child": "satakunta",
        "area": 2.3166299999999955,
        "bounding_box": [
          21.329,
          60.901,
          22.972,
          62.311
        ],
        "point": [
          22.1505,
          61.606
        ],
        "labels": {
          "en": "Satakunta"
        },
        "population": 219867
      }
    },
    {
      "type": "Feature",
      "geometry": {
        "type": "Point",
        "coordinates": [
          22.240000000000002,
          62.9005
        ]
      },
      "properties": {
        "region_schema": "fi_health_district",
        "region_parent": "fi",
        "region_child": "vaasa",
        "area": 4.414475999999996,
        "bounding_box": [
          21.074,
          61.954,
          23.406,
          63.847
        ],
        "point": [
          22.240000000000002,
          62.9005
        ],
        "labels": {
          "en": "Vaasa"
        },
        "population": 169031
      }
    },
    {
      "type": "Feature",
      "geometry": {
        "type": "Point",
        "coordinates": [
          21.277,
          63.2345
        ]
      },
      "properties": {
        "region_schema": "fi_health_district",
        "region_parent": "fi",
        "region_child": "vaasa",
        "area": 0.053630000000000407,
        "bounding_box": [
          21.104,
          63.157,
          21.45,
          63.312
        ],
        "point": [
          21.277,
          63.2345
        ],
        "labels": {
          "en": "Vaasa"
        },
        "population": 169031
      }
    },
    {
      "type": "Feature",
      "geometry": {
        "type": "Point",
        "coordinates": [
          22.153,
          63.298
        ]
      },
      "properties": {
        "region_schema": "fi_health_district",
        "region_parent": "fi",
        "region_child": "vaasa",
        "area": 0.013931999999999983,
        "bounding_box": [
          22.072,
          63.255,
          22.234,
          63.341
        ],
        "point": [
          22.153,
          63.298
        ],
        "labels": {
          "en": "Vaasa"
        },
        "population": 169031
      }
    },
    {
      "type": "Feature",
      "geometry": {
        "type": "Point",
        "coordinates": [
          21.3335,
          63.339
        ]
      },
      "properties": {
        "region_schema": "fi_health_district",
        "region_parent": "fi",
        "region_child": "vaasa",
        "area": 0.01068800000000011,
        "bounding_box": [
          21.25,
          63.307,
          21.417,
          63.371
        ],
        "point": [
          21.3335,
          63.339
        ],
        "labels": {
          "en": "Vaasa"
        },
        "population": 169031
      }
    },
    {
      "type": "Feature",
      "geometry": {
        "type": "Point",
        "coordinates": [
          22.031,
          63.3655
        ]
      },
      "properties": {
        "region_schema": "fi_health_district",
        "region_parent": "fi",
        "region_child": "vaasa",
        "area": 0.006678000000000617,
        "bounding_box": [
          21.968,
          63.339,
          22.094,
          63.392
        ],
        "point": [
          22.031,
          63.3655
        ],
        "labels": {
          "en": "Vaasa"
        },
        "population": 169031
      }
    },
    {
      "type": "Feature",
      "geometry": {
        "type": "Point",
        "coordinates": [
          21.180999999999997,
          62.977000000000004
        ]
      },
      "properties": {
        "region_schema": "fi_health_district",
        "region_parent": "fi",
        "region_child": "vaasa",
        "area": 0.004480000000000463,
        "bounding_box": [
          21.141,
          62.949,
          21.221,
          63.005
        ],
        "point": [
          21.180999999999997,
          62.977000000000004
        ],
        "labels": {
          "en": "Vaasa"
        },
        "population": 169031
      }
    },
    {
      "type": "Feature",
      "geometry": {
        "type": "Point",
        "coordinates": [
          21.1595,
          62.8485
        ]
      },
      "properties": {
        "region_schema": "fi_health_district",
        "region_parent": "fi",
        "region_child": "vaasa",
        "area": 0.004304999999999619,
        "bounding_box": [
          21.098,
          62.831,
          21.221,
          62.866
        ],
        "point": [
          21.1595,
          62.8485
        ],
        "labels": {
          "en": "Vaasa"
        },
        "population": 169031
      }
    },
    {
      "type": "Feature",
      "geometry": {
        "type": "Point",
        "coordinates": [
          21.3915,
          63.0375
        ]
      },
      "properties": {
        "region_schema": "fi_health_district",
        "region_parent": "fi",
        "region_child": "vaasa",
        "area": 0.003003000000000043,
        "bounding_box": [
          21.353,
          63.018,
          21.43,
          63.057
        ],
        "point": [
          21.3915,
          63.0375
        ],
        "labels": {
          "en": "Vaasa"
        },
        "population": 169031
      }
    },
    {
      "type": "Feature",
      "geometry": {
        "type": "Point",
        "coordinates": [
          22.548000000000002,
          60.6495
        ]
      },
      "properties": {
        "region_schema": "fi_health_district",
        "region_parent": "fi",
        "region_child": "varsinais-suomi",
        "area": 3.0782660000000046,
        "bounding_box": [
          21.175,
          60.089,
          23.921,
          61.21
        ],
        "point": [
          22.548000000000002,
          60.6495
        ],
        "labels": {
          "en": "Varsinais-Suomi"
        },
        "population": 463868
      }
    },
    {
      "type": "Feature",
      "geometry": {
        "type": "Point",
        "coordinates": [
          22.674500000000002,
          60.1515
        ]
      },
      "properties": {
        "region_schema": "fi_health_district",
        "region_parent": "fi",
        "region_child": "varsinais-suomi",
        "area": 0.1850810000000007,
        "bounding_box": [
          22.365,
          60.002,
          22.984,
          60.301
        ],
        "point": [
          22.674500000000002,
          60.1515
        ],
        "labels": {
          "en": "Varsinais-Suomi"
        },
        "population": 463868
      }
    },
    {
      "type": "Feature",
      "geometry": {
        "type": "Point",
        "coordinates": [
          21.9205,
          60.416
        ]
      },
      "properties": {
        "region_schema": "fi_health_district",
        "region_parent": "fi",
        "region_child": "varsinais-suomi",
        "area": 0.038332000000000886,
        "bounding_box": [
          21.791,
          60.342,
          22.05,
          60.49
        ],
        "point": [
          21.9205,
          60.416
        ],
        "labels": {
          "en": "Varsinais-Suomi"
        },
        "population": 463868
      }
    },
    {
      "type": "Feature",
      "geometry": {
        "type": "Point",
        "coordinates": [
          21.820999999999998,
          60.1745
        ]
      },
      "properties": {
        "region_schema": "fi_health_district",
        "region_parent": "fi",
        "region_child": "varsinais-suomi",
        "area": 0.02184999999999978,
        "bounding_box": [
          21.706,
          60.127,
          21.936,
          60.222
        ],
        "point": [
          21.820999999999998,
          60.1745
        ],
        "labels": {
          "en": "Varsinais-Suomi"
        },
        "population": 463868
      }
    },
    {
      "type": "Feature",
      "geometry": {
        "type": "Point",
        "coordinates": [
          21.427999999999997,
          60.54
        ]
      },
      "properties": {
        "region_schema": "fi_health_district",
        "region_parent": "fi",
        "region_child": "varsinais-suomi",
        "area": 0.021168000000000964,
        "bounding_box": [
          21.33,
          60.486,
          21.526,
          60.594
        ],
        "point": [
          21.427999999999997,
          60.54
        ],
        "labels": {
          "en": "Varsinais-Suomi"
        },
        "population": 463868
      }
    },
    {
      "type": "Feature",
      "geometry": {
        "type": "Point",
        "coordinates": [
          22.195,
          60.2945
        ]
      },
      "properties": {
        "region_schema": "fi_health_district",
        "region_parent": "fi",
        "region_child": "varsinais-suomi",
        "area": 0.01663199999999969,
        "bounding_box": [
          22.087,
          60.256,
          22.303,
          60.333
        ],
        "point": [
          22.195,
          60.2945
        ],
        "labels": {
          "en": "Varsinais-Suomi"
        },
        "population": 463868
      }
    },
    {
      "type": "Feature",
      "geometry": {
        "type": "Point",
        "coordinates": [
          22.4105,
          60.338499999999996
        ]
      },
      "properties": {
        "region_schema": "fi_health_district",
        "region_parent": "fi",
        "region_child": "varsinais-suomi",
        "area": 0.01400300000000001,
        "bounding_box": [
          22.306,
          60.305,
          22.515,
          60.372
        ],
        "point": [
          22.4105,
          60.338499999999996
        ],
        "labels": {
          "en": "Varsinais-Suomi"
        },
        "population": 463868
      }
    },
    {
      "type": "Feature",
      "geometry": {
        "type": "Point",
        "coordinates": [
          21.6,
          60.147999999999996
        ]
      },
      "properties": {
        "region_schema": "fi_health_district",
        "region_parent": "fi",
        "region_child": "varsinais-suomi",
        "area": 0.013072000000000134,
        "bounding_box": [
          21.514,
          60.11,
          21.686,
          60.186
        ],
        "point": [
          21.6,
          60.147999999999996
        ],
        "labels": {
          "en": "Varsinais-Suomi"
        },
        "population": 463868
      }
    },
    {
      "type": "Feature",
      "geometry": {
        "type": "Point",
        "coordinates": [
          22.386499999999998,
          60.271
        ]
      },
      "properties": {
        "region_schema": "fi_health_district",
        "region_parent": "fi",
        "region_child": "varsinais-suomi",
        "area": 0.010403999999999821,
        "bounding_box": [
          22.31,
          60.237,
          22.463,
          60.305
        ],
        "point": [
          22.386499999999998,
          60.271
        ],
        "labels": {
          "en": "Varsinais-Suomi"
        },
        "population": 463868
      }
    },
    {
      "type": "Feature",
      "geometry": {
        "type": "Point",
        "coordinates": [
          22.016,
          60.185500000000005
        ]
      },
      "properties": {
        "region_schema": "fi_health_district",
        "region_parent": "fi",
        "region_child": "varsinais-suomi",
        "area": 0.008906000000000299,
        "bounding_box": [
          21.955,
          60.149,
          22.077,
          60.222
        ],
        "point": [
          22.016,
          60.185500000000005
        ],
        "labels": {
          "en": "Varsinais-Suomi"
        },
        "population": 463868
      }
    },
    {
      "type": "Feature",
      "geometry": {
        "type": "Point",
        "coordinates": [
          22.268,
          60.234
        ]
      },
      "properties": {
        "region_schema": "fi_health_district",
        "region_parent": "fi",
        "region_child": "varsinais-suomi",
        "area": 0.008731999999999927,
        "bounding_box": [
          22.209,
          60.197,
          22.327,
          60.271
        ],
        "point": [
          22.268,
          60.234
        ],
        "labels": {
          "en": "Varsinais-Suomi"
        },
        "population": 463868
      }
    },
    {
      "type": "Feature",
      "geometry": {
        "type": "Point",
        "coordinates": [
          21.2945,
          60.536500000000004
        ]
      },
      "properties": {
        "region_schema": "fi_health_district",
        "region_parent": "fi",
        "region_child": "varsinais-suomi",
        "area": 0.00861299999999964,
        "bounding_box": [
          21.245,
          60.493,
          21.344,
          60.58
        ],
        "point": [
          21.2945,
          60.536500000000004
        ],
        "labels": {
          "en": "Varsinais-Suomi"
        },
        "population": 463868
      }
    },
    {
      "type": "Feature",
      "geometry": {
        "type": "Point",
        "coordinates": [
          21.2725,
          60.626000000000005
        ]
      },
      "properties": {
        "region_schema": "fi_health_district",
        "region_parent": "fi",
        "region_child": "varsinais-suomi",
        "area": 0.007475999999999536,
        "bounding_box": [
          21.228,
          60.584,
          21.317,
          60.668
        ],
        "point": [
          21.2725,
          60.626000000000005
        ],
        "labels": {
          "en": "Varsinais-Suomi"
        },
        "population": 463868
      }
    },
    {
      "type": "Feature",
      "geometry": {
        "type": "Point",
        "coordinates": [
          21.361,
          60.210499999999996
        ]
      },
      "properties": {
        "region_schema": "fi_health_district",
        "region_parent": "fi",
        "region_child": "varsinais-suomi",
        "area": 0.007426000000000714,
        "bounding_box": [
          21.282,
          60.187,
          21.44,
          60.234
        ],
        "point": [
          21.361,
          60.210499999999996
        ],
        "labels": {
          "en": "Varsinais-Suomi"
        },
        "population": 463868
      }
    },
    {
      "type": "Feature",
      "geometry": {
        "type": "Point",
        "coordinates": [
          22.0035,
          60.451
        ]
      },
      "properties": {
        "region_schema": "fi_health_district",
        "region_parent": "fi",
        "region_child": "varsinais-suomi",
        "area": 0.006999999999999673,
        "bounding_box": [
          21.941,
          60.423,
          22.066,
          60.479
        ],
        "point": [
          22.0035,
          60.451
        ],
        "labels": {
          "en": "Varsinais-Suomi"
        },
        "population": 463868
      }
    },
    {
      "type": "Feature",
      "geometry": {
        "type": "Point",
        "coordinates": [
          22.395,
          60.3865
        ]
      },
      "properties": {
        "region_schema": "fi_health_district",
        "region_parent": "fi",
        "region_child": "varsinais-suomi",
        "area": 0.006277999999999926,
        "bounding_box": [
          22.322,
          60.365,
          22.468,
          60.408
        ],
        "point": [
          22.395,
          60.3865
        ],
        "labels": {
          "en": "Varsinais-Suomi"
        },
        "population": 463868
      }
    },
    {
      "type": "Feature",
      "geometry": {
        "type": "Point",
        "coordinates": [
          22.229,
          60.359
        ]
      },
      "properties": {
        "region_schema": "fi_health_district",
        "region_parent": "fi",
        "region_child": "varsinais-suomi",
        "area": 0.005544000000000207,
        "bounding_box": [
          22.152,
          60.341,
          22.306,
          60.377
        ],
        "point": [
          22.229,
          60.359
        ],
        "labels": {
          "en": "Varsinais-Suomi"
        },
        "population": 463868
      }
    },
    {
      "type": "Feature",
      "geometry": {
        "type": "Point",
        "coordinates": [
          22.918,
          60.102000000000004
        ]
      },
      "properties": {
        "region_schema": "fi_health_district",
        "region_parent": "fi",
        "region_child": "varsinais-suomi",
        "area": 0.004488000000000426,
        "bounding_box": [
          22.867,
          60.08,
          22.969,
          60.124
        ],
        "point": [
          22.918,
          60.102000000000004
        ],
        "labels": {
          "en": "Varsinais-Suomi"
        },
        "population": 463868
      }
    },
    {
      "type": "Feature",
      "geometry": {
        "type": "Point",
        "coordinates": [
          22.198,
          60.411
        ]
      },
      "properties": {
        "region_schema": "fi_health_district",
        "region_parent": "fi",
        "region_child": "varsinais-suomi",
        "area": 0.004368000000000132,
        "bounding_box": [
          22.146,
          60.39,
          22.25,
          60.432
        ],
        "point": [
          22.198,
          60.411
        ],
        "labels": {
          "en": "Varsinais-Suomi"
        },
        "population": 463868
      }
    },
    {
      "type": "Feature",
      "geometry": {
        "type": "Point",
        "coordinates": [
          22.883,
          60.045
        ]
      },
      "properties": {
        "region_schema": "fi_health_district",
        "region_parent": "fi",
        "region_child": "varsinais-suomi",
        "area": 0.003360000000000141,
        "bounding_box": [
          22.848,
          60.021,
          22.918,
          60.069
        ],
        "point": [
          22.883,
          60.045
        ],
        "labels": {
          "en": "Varsinais-Suomi"
        },
        "population": 463868
      }
    },
    {
      "type": "Feature",
      "geometry": {
        "type": "Point",
        "coordinates": [
          21.743499999999997,
          60.5275
        ]
      },
      "properties": {
        "region_schema": "fi_health_district",
        "region_parent": "fi",
        "region_child": "varsinais-suomi",
        "area": 0.0025830000000001993,
        "bounding_box": [
          21.712,
          60.507,
          21.775,
          60.548
        ],
        "point": [
          21.743499999999997,
          60.5275
        ],
        "labels": {
          "en": "Varsinais-Suomi"
        },
        "population": 463868
      }
    }
  ]
}