{
  "type": "FeatureCollection",
  "features": [
    {
      "type": "Feature",
      "geometry": {
        "type": "Point",
        "coordinates": [
          136.05700000000002,
          35.95
        ]
      },
      "properties": {
        "region_schema": "jp_city",
        "region_parent": "jp-18",
        "region_child": "18423",
        "area": 0.030888000000000936,
        "bounding_box": [
          135.958,
          35.872,
          136.156,
          36.028
        ],
        "point": [
          136.05700000000002,
          35.95
        ],
        "labels": {
          "ja": "越前町",
          "en": "echizen-cho"
        },
        "population": 21718
      }
    },
    {
      "type": "Feature",
      "geometry": {
        "type": "Point",
        "coordinates": [
          136.18349999999998,
          35.7695
        ]
      },
      "properties": {
        "region_schema": "jp_city",
        "region_parent": "jp-18",
        "region_child": "18404",
        "area": 0.07486499999999932,
        "bounding_box": [
          136.011,
          35.661,
          136.356,
          35.878
        ],
        "point": [
          136.18349999999998,
          35.7695
        ],
        "labels": {
          "ja": "南越前町",
          "en": "minamiechizen-cho"
        },
        "population": 11046
      }
    },
    {
      "type": "Feature",
      "geometry": {
        "type": "Point",
        "coordinates": [
          136.17700000000002,
          35.878
        ]
      },
      "properties": {
        "region_schema": "jp_city",
        "region_parent": "jp-18",
        "region_child": "18209",
        "area": 0.043959999999999194,
        "bounding_box": [
          136.02,
          35.808,
          136.334,
          35.948
        ],
        "point": [
          136.17700000000002,
          35.878
        ],
        "labels": {
          "ja": "越前市",
          "en": "echizen-shi"
        },
        "population": 83455
      }
    },
    {
      "type": "Feature",
      "geometry": {
        "type": "Point",
        "coordinates": [
          136.26999999999998,
          36.1795
        ]
      },
      "properties": {
        "region_schema": "jp_city",
        "region_parent": "jp-18",
        "region_child": "18210",
        "area": 0.05270000000000091,
        "bounding_box": [
          136.1,
          36.102,
          136.44,
          36.257
        ],
        "point": [
          136.26999999999998,
          36.1795
        ],
        "labels": {
          "ja": "坂井市",
          "en": "sakai-shi"
        },
        "population": 84401
      }
    },
    {
      "type": "Feature",
      "geometry": {
        "type": "Point",
        "coordinates": [
          136.119,
          36.251999999999995
        ]
      },
      "properties": {
        "region_schema": "jp_city",
        "region_parent": "jp-18",
        "region_child": "18210",
        "area": 1.600000000006753e-05,
        "bounding_box": [
          136.117,
          36.25,
          136.121,
          36.254
        ],
        "point": [
          136.119,
          36.251999999999995
        ],
        "labels": {
          "ja": "坂井市",
          "en": "sakai-shi"
        },
        "population": 84401
      }
    },
    {
      "type": "Feature",
      "geometry": {
        "type": "Point",
        "coordinates": [
          136.1455,
          36.254
        ]
      },
      "properties": {
        "region_schema": "jp_city",
        "region_parent": "jp-18",
        "region_child": "18210",
        "area": 0.0,
        "bounding_box": [
          136.145,
          36.254,
          136.146,
          36.254
        ],
        "point": [
          136.1455,
          36.254
        ],
        "labels": {
          "ja": "坂井市",
          "en": "sakai-shi"
        },
        "population": 84401
      }
    },
    {
      "type": "Feature",
      "geometry": {
        "type": "Point",
        "coordinates": [
          136.147,
          36.2555
        ]
      },
      "properties": {
        "region_schema": "jp_city",
        "region_parent": "jp-18",
        "region_child": "18210",
        "area": 0.0,
        "bounding_box": [
          136.147,
          36.255,
          136.147,
          36.256
        ],
        "point": [
          136.147,
          36.2555
        ],
        "labels": {
          "ja": "坂井市",
          "en": "sakai-shi"
        },
        "population": 84401
      }
    },
    {
      "type": "Feature",
      "geometry": {
        "type": "Point",
        "coordinates": [
          135.9225,
          35.6085
        ]
      },
      "properties": {
        "region_schema": "jp_city",
        "region_parent": "jp-18",
        "region_child": "18442",
        "area": 0.05224499999999975,
        "bounding_box": [
          135.815,
          35.487,
          136.03,
          35.73
        ],
        "point": [
          135.9225,
          35.6085
        ],
        "labels": {
          "ja": "美浜町",
          "en": "mihama-cho"
        },
        "population": 9548
      }
    },
    {
      "type": "Feature",
      "geometry": {
        "type": "Point",
        "coordinates": [
          135.639,
          35.415
        ]
      },
      "properties": {
        "region_schema": "jp_city",
        "region_parent": "jp-18",
        "region_child": "18483",
        "area": 0.04345200000000039,
        "bounding_box": [
          135.486,
          35.344,
          135.792,
          35.486
        ],
        "point": [
          135.639,
          35.415
        ],
        "labels": {
          "ja": "おおい町",
          "en": "oi-cho"
        },
        "population": 7102
      }
    },
    {
      "type": "Feature",
      "geometry": {
        "type": "Point",
        "coordinates": [
          135.63600000000002,
          35.5185
        ]
      },
      "properties": {
        "region_schema": "jp_city",
        "region_parent": "jp-18",
        "region_child": "18483",
        "area": 0.0038940000000004514,
        "bounding_box": [
          135.603,
          35.489,
          135.669,
          35.548
        ],
        "point": [
          135.63600000000002,
          35.5185
        ],
        "labels": {
          "ja": "おおい町",
          "en": "oi-cho"
        },
        "population": 7102
      }
    },
    {
      "type": "Feature",
      "geometry": {
        "type": "Point",
        "coordinates": [
          135.67000000000002,
          35.5245
        ]
      },
      "properties": {
        "region_schema": "jp_city",
        "region_parent": "jp-18",
        "region_child": "18483",
        "area": 1.999999999976467e-06,
        "bounding_box": [
          135.669,
          35.524,
          135.671,
          35.525
        ],
        "point": [
          135.67000000000002,
          35.5245
        ],
        "labels": {
          "ja": "おおい町",
          "en": "oi-cho"
        },
        "population": 7102
      }
    },
    {
      "type": "Feature",
      "geometry": {
        "type": "Point",
        "coordinates": [
          135.6495,
          35.5215
        ]
      },
      "properties": {
        "region_schema": "jp_city",
        "region_parent": "jp-18",
        "region_child": "18483",
        "area": 1.0000000000024443e-06,
        "bounding_box": [
          135.649,
          35.521,
          135.65,
          35.522
        ],
        "point": [
          135.6495,
          35.5215
        ],
        "labels": {
          "ja": "おおい町",
          "en": "oi-cho"
        },
        "population": 7102
      }
    },
    {
      "type": "Feature",
      "geometry": {
        "type": "Point",
        "coordinates": [
          135.655,
          35.546499999999995
        ]
      },
      "properties": {
        "region_schema": "jp_city",
        "region_parent": "jp-18",
        "region_child": "18483",
        "area": 0.0,
        "bounding_box": [
          135.655,
          35.546,
          135.655,
          35.547
        ],
        "point": [
          135.655,
          35.546499999999995
        ],
        "labels": {
          "ja": "おおい町",
          "en": "oi-cho"
        },
        "population": 7102
      }
    },
    {
      "type": "Feature",
      "geometry": {
        "type": "Point",
        "coordinates": [
          136.5235,
          36.083
        ]
      },
      "properties": {
        "region_schema": "jp_city",
        "region_parent": "jp-18",
        "region_child": "18206",
        "area": 0.04119199999999824,
        "bounding_box": [
          136.388,
          36.007,
          136.659,
          36.159
        ],
        "point": [
          136.5235,
          36.083
        ],
        "labels": {
          "ja": "勝山市",
          "en": "katsuyama-shi"
        },
        "population": 24952
      }
    },
    {
      "type": "Feature",
      "geometry": {
        "type": "Point",
        "coordinates": [
          136.624,
          35.918
        ]
      },
      "properties": {
        "region_schema": "jp_city",
        "region_parent": "jp-18",
        "region_child": "18205",
        "area": 0.13977599999999832,
        "bounding_box": [
          136.416,
          35.75,
          136.832,
          36.086
        ],
        "point": [
          136.624,
          35.918
        ],
        "labels": {
          "ja": "大野市",
          "en": "ono-shi"
        },
        "population": 33424
      }
    },
    {
      "type": "Feature",
      "geometry": {
        "type": "Point",
        "coordinates": [
          136.2305,
          35.965
        ]
      },
      "properties": {
        "region_schema": "jp_city",
        "region_parent": "jp-18",
        "region_child": "18207",
        "area": 0.015191999999999994,
        "bounding_box": [
          136.125,
          35.929,
          136.336,
          36.001
        ],
        "point": [
          136.2305,
          35.965
        ],
        "labels": {
          "ja": "鯖江市",
          "en": "sabae-shi"
        },
        "population": 63987
      }
    },
    {
      "type": "Feature",
      "geometry": {
        "type": "Point",
        "coordinates": [
          136.071,
          35.6455
        ]
      },
      "properties": {
        "region_schema": "jp_city",
        "region_parent": "jp-18",
        "region_child": "18202",
        "area": 0.0506679999999968,
        "bounding_box": [
          135.965,
          35.526,
          136.177,
          35.765
        ],
        "point": [
          136.071,
          35.6455
        ],
        "labels": {
          "ja": "敦賀市",
          "en": "tsuruga-shi"
        },
        "population": 63733
      }
    },
    {
      "type": "Feature",
      "geometry": {
        "type": "Point",
        "coordinates": [
          135.875,
          35.518
        ]
      },
      "properties": {
        "region_schema": "jp_city",
        "region_parent": "jp-18",
        "region_child": "18501",
        "area": 0.03918400000000457,
        "bounding_box": [
          135.796,
          35.394,
          135.954,
          35.642
        ],
        "point": [
          135.875,
          35.518
        ],
        "labels": {
          "ja": "若狭町",
          "en": "wakasa-cho"
        },
        "population": 15549
      }
    },
    {
      "type": "Feature",
      "geometry": {
        "type": "Point",
        "coordinates": [
          135.805,
          35.6345
        ]
      },
      "properties": {
        "region_schema": "jp_city",
        "region_parent": "jp-18",
        "region_child": "18501",
        "area": 5.400000000000409e-05,
        "bounding_box": [
          135.802,
          35.63,
          135.808,
          35.639
        ],
        "point": [
          135.805,
          35.6345
        ],
        "labels": {
          "ja": "若狭町",
          "en": "wakasa-cho"
        },
        "population": 15549
      }
    },
    {
      "type": "Feature",
      "geometry": {
        "type": "Point",
        "coordinates": [
          135.836,
          35.5785
        ]
      },
      "properties": {
        "region_schema": "jp_city",
        "region_parent": "jp-18",
        "region_child": "18501",
        "area": 1.1999999999972487e-05,
        "bounding_box": [
          135.834,
          35.577,
          135.838,
          35.58
        ],
        "point": [
          135.836,
          35.5785
        ],
        "labels": {
          "ja": "若狭町",
          "en": "wakasa-cho"
        },
        "population": 15549
      }
    },
    {
      "type": "Feature",
      "geometry": {
        "type": "Point",
        "coordinates": [
          135.833,
          35.602
        ]
      },
      "properties": {
        "region_schema": "jp_city",
        "region_parent": "jp-18",
        "region_child": "18501",
        "area": 0.0,
        "bounding_box": [
          135.833,
          35.602,
          135.833,
          35.602
        ],
        "point": [
          135.833,
          35.602
        ],
        "labels": {
          "ja": "若狭町",
          "en": "wakasa-cho"
        },
        "population": 15549
      }
    },
    {
      "type": "Feature",
      "geometry": {
        "type": "Point",
        "coordinates": [
          135.828,
          35.607
        ]
      },
      "properties": {
        "region_schema": "jp_city",
        "region_parent": "jp-18",
        "region_child": "18501",
        "area": 0.0,
        "bounding_box": [
          135.828,
          35.607,
          135.828,
          35.607
        ],
        "point": [
          135.828,
          35.607
        ],
        "labels": {
          "ja": "若狭町",
          "en": "wakasa-cho"
        },
        "population": 15549
      }
    },
    {
      "type": "Feature",
      "geometry": {
        "type": "Point",
        "coordinates": [
          136.3585,
          35.866
        ]
      },
      "properties": {
        "region_schema": "jp_city",
        "region_parent": "jp-18",
        "region_child": "18382",
        "area": 0.03526000000000155,
        "bounding_box": [
          136.256,
          35.78,
          136.461,
          35.952
        ],
        "point": [
          136.3585,
          35.866
        ],
        "labels": {
          "ja": "池田町",
          "en": "ikeda-cho"
        },
        "population": 3005
      }
    },
    {
      "type": "Feature",
      "geometry": {
        "type": "Point",
        "coordinates": [
          135.7245,
          35.4805
        ]
      },
      "properties": {
        "region_schema": "jp_city",
        "region_parent": "jp-18",
        "region_child": "18204",
        "area": 0.05230300000000231,
        "bounding_box": [
          135.589,
          35.384,
          135.86,
          35.577
        ],
        "point": [
          135.7245,
          35.4805
        ],
        "labels": {
          "ja": "小浜市",
          "en": "obama-shi"
        },
        "population": 28404
      }
    },
    {
      "type": "Feature",
      "geometry": {
        "type": "Point",
        "coordinates": [
          135.68349999999998,
          35.498000000000005
        ]
      },
      "properties": {
        "region_schema": "jp_city",
        "region_parent": "jp-18",
        "region_child": "18204",
        "area": 2.000000000011994e-06,
        "bounding_box": [
          135.683,
          35.497,
          135.684,
          35.499
        ],
        "point": [
          135.68349999999998,
          35.498000000000005
        ],
        "labels": {
          "ja": "小浜市",
          "en": "obama-shi"
        },
        "population": 28404
      }
    },
    {
      "type": "Feature",
      "geometry": {
        "type": "Point",
        "coordinates": [
          136.3545,
          36.0815
        ]
      },
      "properties": {
        "region_schema": "jp_city",
        "region_parent": "jp-18",
        "region_child": "18322",
        "area": 0.016054999999998168,
        "bounding_box": [
          136.27,
          36.034,
          136.439,
          36.129
        ],
        "point": [
          136.3545,
          36.0815
        ],
        "labels": {
          "ja": "永平寺町",
          "en": "eiheiji-cho"
        },
        "population": 19821
      }
    },
    {
      "type": "Feature",
      "geometry": {
        "type": "Point",
        "coordinates": [
          136.25,
          36.235
        ]
      },
      "properties": {
        "region_schema": "jp_city",
        "region_parent": "jp-18",
        "region_child": "18208",
        "area": 0.01967999999999922,
        "bounding_box": [
          136.168,
          36.175,
          136.332,
          36.295
        ],
        "point": [
          136.25,
          36.235
        ],
        "labels": {
          "ja": "あわら市",
          "en": "awara-shi"
        },
        "population": 29303
      }
    },
    {
      "type": "Feature",
      "geometry": {
        "type": "Point",
        "coordinates": [
          136.21550000000002,
          36.0465
        ]
      },
      "properties": {
        "region_schema": "jp_city",
        "region_parent": "jp-18",
        "region_child": "18201",
        "area": 0.12725900000000367,
        "bounding_box": [
          135.964,
          35.92,
          136.467,
          36.173
        ],
        "point": [
          136.21550000000002,
          36.0465
        ],
        "labels": {
          "ja": "福井市",
          "en": "fukui-shi"
        },
        "population": 257257
      }
    },
    {
      "type": "Feature",
      "geometry": {
        "type": "Point",
        "coordinates": [
          136.0505,
          36.1255
        ]
      },
      "properties": {
        "region_schema": "jp_city",
        "region_parent": "jp-18",
        "region_child": "18201",
        "area": 8.99999999995805e-06,
        "bounding_box": [
          136.049,
          36.124,
          136.052,
          36.127
        ],
        "point": [
          136.0505,
          36.1255
        ],
        "labels": {
          "ja": "福井市",
          "en": "fukui-shi"
        },
        "population": 257257
      }
    },
    {
      "type": "Feature",
      "geometry": {
        "type": "Point",
        "coordinates": [
          136.04649999999998,
          36.1155
        ]
      },
      "properties": {
        "region_schema": "jp_city",
        "region_parent": "jp-18",
        "region_child": "18201",
        "area": 1.0000000000024443e-06,
        "bounding_box": [
          136.046,
          36.115,
          136.047,
          36.116
        ],
        "point": [
          136.04649999999998,
          36.1155
        ],
        "labels": {
          "ja": "福井市",
          "en": "fukui-shi"
        },
        "population": 257257
      }
    },
    {
      "type": "Feature",
      "geometry": {
        "type": "Point",
        "coordinates": [
          136.0625,
          36.1325
        ]
      },
      "properties": {
        "region_schema": "jp_city",
        "region_parent": "jp-18",
        "region_child": "18201",
        "area": 9.99999999981128e-07,
        "bounding_box": [
          136.062,
          36.132,
          136.063,
          36.133
        ],
        "point": [
          136.0625,
          36.1325
        ],
        "labels": {
          "ja": "福井市",
          "en": "fukui-shi"
        },
        "population": 257257
      }
    },
    {
      "type": "Feature",
      "geometry": {
        "type": "Point",
        "coordinates": [
          135.53,
          35.503
        ]
      },
      "properties": {
        "region_schema": "jp_city",
        "region_parent": "jp-18",
        "region_child": "18481",
        "area": 0.017819999999997456,
        "bounding_box": [
          135.449,
          35.448,
          135.611,
          35.558
        ],
        "point": [
          135.53,
          35.503
        ],
        "labels": {
          "ja": "高浜町",
          "en": "takahama-cho"
        },
        "population": 9852
      }
    },
    {
      "type": "Feature",
      "geometry": {
        "type": "Point",
        "coordinates": [
          135.54649999999998,
          35.4955
        ]
      },
      "properties": {
        "region_schema": "jp_city",
        "region_parent": "jp-18",
        "region_child": "18481",
        "area": 3.0000000000286493e-06,
        "bounding_box": [
          135.545,
          35.495,
          135.548,
          35.496
        ],
        "point": [
          135.54649999999998,
          35.4955
        ],
        "labels": {
          "ja": "高浜町",
          "en": "takahama-cho"
        },
        "population": 9852
      }
    },
    {
      "type": "Feature",
      "geometry": {
        "type": "Point",
        "coordinates": [
          135.51850000000002,
          35.5355
        ]
      },
      "properties": {
        "region_schema": "jp_city",
        "region_parent": "jp-18",
        "region_child": "18481",
        "area": 1.0000000000095496e-06,
        "bounding_box": [
          135.518,
          35.535,
          135.519,
          35.536
        ],
        "point": [
          135.51850000000002,
          35.5355
        ],
        "labels": {
          "ja": "高浜町",
          "en": "takahama-cho"
        },
        "population": 9852
      }
    }
  ]
}